abinitostudio/__init__.py
abinitostudio/myMainWindow.py
abinitostudio/calculation/__init__.py
abinitostudio/calculation/vasp_calculation.py
abinitostudio/images/about.png
abinitostudio/images/band.png
abinitostudio/images/band_noncal.png
abinitostudio/images/close.png
abinitostudio/images/dos.png
abinitostudio/images/energy_band.png
abinitostudio/images/phonon.png
abinitostudio/images/projected_bands.png
abinitostudio/images/scf.png
abinitostudio/images/scf_noncal.png
abinitostudio/images/setting.png
abinitostudio/images/startup.jpg
abinitostudio/images/structure.png
abinitostudio/images/supercell.png
abinitostudio/images/test.png
abinitostudio/images/vasp.png
abinitostudio/images/view_3d.png
abinitostudio/images/wannier.png
abinitostudio/images/层级.png
abinitostudio/images/能带图.png
abinitostudio/images/说明.png
abinitostudio/io/__init__.py
abinitostudio/io/vasp_io.py
abinitostudio/plot/__init__.py
abinitostudio/plot/plot_field.py
abinitostudio/plot/plot_vasp.py
abinitostudio/structure/__init__.py
abinitostudio/structure/plot_structure.py
abinitostudio/structure/tabdialog.py
abinitostudio/ui/Dialog_DOS.py
abinitostudio/ui/Dialog_PB.py
abinitostudio/ui/Dialog_band.py
abinitostudio/ui/UI.py
abinitostudio/ui/UI_setting.py
abinitostudio/ui/UI_test.py
abinitostudio/ui/UI_vasp_DOS.py
abinitostudio/ui/UI_vasp_band.py
abinitostudio/ui/UI_vasp_band_noncal.py
abinitostudio/ui/UI_vasp_phonon.py
abinitostudio/ui/UI_vasp_scf.py
abinitostudio/ui/UI_vasp_scf_noncal.py
abinitostudio/ui/UI_vasp_supercell.py
abinitostudio/ui/UI_vasp_wannier.py
abinitostudio/ui/__init__.py
abinitostudio-1.0.8.data/scripts/appMain.py
abinitostudio-1.0.8.data/scripts/cal_vasp_single.py
abinitostudio-1.0.8.dist-info/LICENSE
abinitostudio-1.0.8.dist-info/METADATA
abinitostudio-1.0.8.dist-info/WHEEL
abinitostudio-1.0.8.dist-info/top_level.txt
abinitostudio-1.0.8.dist-info/RECORD
